<Alloy>
	<View id="Wrapper" name="Settings">
		<Require type="widget" src="com.mcongrove.navigationBar" id="NavigationBar" text="Archivio Teatro Regio" />
		
		<ScrollView id="container">
			<Label id="loginheader" text="login" />
			<ImageView id="image" image="/image/cadre-plus-ipad.png" />
			<View id="alertmessage">
				<Label id="message" />
			</View>
			<View id="loginform">
				<TextField id="loginfield"/>
				<TextField id="passwordfield"/>
				<Button id="loginbutton"/>
			</View>
		</ScrollView>
	</View>
</Alloy>